odoo10_addon_website_sale_charge_payment_fee_quote-10.0.1.0.0.99.dev5-py3.8-nspkg.pth
odoo/addons/website_sale_charge_payment_fee_quote/README.rst
odoo/addons/website_sale_charge_payment_fee_quote/__init__.py
odoo/addons/website_sale_charge_payment_fee_quote/__manifest__.py
odoo/addons/website_sale_charge_payment_fee_quote/controllers/__init__.py
odoo/addons/website_sale_charge_payment_fee_quote/controllers/website_quote.py
odoo/addons/website_sale_charge_payment_fee_quote/i18n/website_sale_charge_payment_fee_quote.pot
odoo/addons/website_sale_charge_payment_fee_quote/readme/CONTRIBUTORS.rst
odoo/addons/website_sale_charge_payment_fee_quote/readme/DESCRIPTION.rst
odoo/addons/website_sale_charge_payment_fee_quote/static/description/icon.png
odoo/addons/website_sale_charge_payment_fee_quote/static/description/index.html
odoo/addons/website_sale_charge_payment_fee_quote/static/src/js/website_quote_fee.js
odoo/addons/website_sale_charge_payment_fee_quote/views/website_quote_templates.xml
odoo10_addon_website_sale_charge_payment_fee_quote-10.0.1.0.0.99.dev5.dist-info/METADATA
odoo10_addon_website_sale_charge_payment_fee_quote-10.0.1.0.0.99.dev5.dist-info/WHEEL
odoo10_addon_website_sale_charge_payment_fee_quote-10.0.1.0.0.99.dev5.dist-info/namespace_packages.txt
odoo10_addon_website_sale_charge_payment_fee_quote-10.0.1.0.0.99.dev5.dist-info/top_level.txt
odoo10_addon_website_sale_charge_payment_fee_quote-10.0.1.0.0.99.dev5.dist-info/RECORD
